TakeBlipPosTagger/__init__.py
TakeBlipPosTagger/data.py
TakeBlipPosTagger/mlflowlogger.py
TakeBlipPosTagger/model.py
TakeBlipPosTagger/process_option.py
TakeBlipPosTagger/utils.py
TakeBlipPosTagger/vocab.py
TakeBlipPosTagger/predict/PosTaggerPredict.py
TakeBlipPosTagger/predict/__init__.py
TakeBlipPosTagger/train/LSTMCRFTrainer.py
TakeBlipPosTagger/train/__init__.py
TakeBlipPosTagger-1.0.7.dist-info/LICENSE
TakeBlipPosTagger-1.0.7.dist-info/METADATA
TakeBlipPosTagger-1.0.7.dist-info/WHEEL
TakeBlipPosTagger-1.0.7.dist-info/top_level.txt
TakeBlipPosTagger-1.0.7.dist-info/RECORD
