Metadata-Version: 2.1
Name: TakeBlipPosTagger
Version: 1.0.7
Summary: PosTagger Package
Home-page: UNKNOWN
Author: Data and Analytics Research
Author-email: analytics.dar@take.net
License: UNKNOWN
Keywords: postagging
Platform: UNKNOWN
Classifier: Programming Language :: Python :: 3
Classifier: License :: OSI Approved :: MIT License
Classifier: Operating System :: OS Independent
Requires-Dist: azureml-core (==1.18.0)
Requires-Dist: gensim (==3.8.3)
Requires-Dist: matplotlib (==3.3.3)
Requires-Dist: numpy (==1.19.1)
Requires-Dist: requests (==2.24.0)
Requires-Dist: scikit-learn (==0.23.2)
Requires-Dist: seaborn (==0.11.1)
Requires-Dist: take-text-preprocess (==0.0.4)
Requires-Dist: torch (==1.7.1)
